markdown_span_attr-0.3.0.dist-info/licenses/LICENSE
span_attr/__init__.py
span_attr/extension.py
markdown_span_attr-0.3.0.dist-info/METADATA
markdown_span_attr-0.3.0.dist-info/WHEEL
markdown_span_attr-0.3.0.dist-info/entry_points.txt
markdown_span_attr-0.3.0.dist-info/top_level.txt
markdown_span_attr-0.3.0.dist-info/RECORD
