Metadata-Version: 2.4
Name: markdown-span-attr
Version: 0.3.0
Summary: Span attribute extension for Python-Markdown
Author-email: Francesca Massarenti <fra.mmenti@inventati.org>
License-Expression: MIT
Project-URL: Repository, https://github.com/frammenti/markdown-span-attr
Project-URL: Issues, https://github.com/frammenti/markdown-span-attr/issues
Keywords: markdown,python-markdown,markdown-extension,mkdocs
Classifier: Operating System :: OS Independent
Classifier: Programming Language :: Python :: 3
Classifier: Programming Language :: Python :: 3.9
Classifier: Programming Language :: Python :: 3.10
Classifier: Programming Language :: Python :: 3.11
Classifier: Programming Language :: Python :: 3.12
Classifier: Programming Language :: Python :: 3.13
Classifier: Topic :: Text Processing :: Markup :: Markdown
Classifier: Topic :: Text Processing :: Markup :: HTML
Classifier: Topic :: Text Processing :: Filters
Classifier: Topic :: Software Development :: Documentation
Classifier: Framework :: MkDocs
Requires-Python: >=3.9
License-File: LICENSE
Requires-Dist: markdown>=3.4
Dynamic: license-file
